{
    "version": 2,
    "configurePresets": [
        {
            "name": "windows-debug",
            "displayName": "Windows x64 Debug",
            "description": "Target Windows x64 in debug mode.",
            "generator": "Ninja",
            "binaryDir": "${sourceDir}/out/build/${presetName}",
            "architecture": {
                "value": "x64",
                "strategy": "external"
            },
            "cacheVariables": {
                "CMAKE_BUILD_TYPE": "Debug",
                "CMAKE_INSTALL_PREFIX": "${sourceDir}/out/install/${presetName}",
                "BN_CORE_LIBRARY": "${sourceDir}",
                "BN_UI_LIBRARY": "${sourceDir}"
            },
            "vendor": {
                "microsoft.com/VisualStudioSettings/CMake/1.0": {
                    "hostOS": [
                        "Windows"
                    ]
                }
            }
        },
        {
            "name": "windows-release",
            "displayName": "Windows x64 Release",
            "description": "Target Windows x64 in release mode.",
            "generator": "Ninja",
            "binaryDir": "${sourceDir}/out/build/${presetName}",
            "architecture": {
                "value": "x64",
                "strategy": "external"
            },
            "cacheVariables": {
                "CMAKE_BUILD_TYPE": "Release",
                "CMAKE_INSTALL_PREFIX": "${sourceDir}/out/install/${presetName}",
                "BN_CORE_LIBRARY": "${sourceDir}",
                "BN_UI_LIBRARY": "${sourceDir}"
            },
            "vendor": {
                "microsoft.com/VisualStudioSettings/CMake/1.0": {
                    "hostOS": [
                        "Windows"
                    ]
                }
            }
        },
        {
            "name": "linux-debug",
            "description": "Target Linux x64 in debug mode.",
            "displayName": "Linux x64 Debug",
            "generator": "Ninja",
            "binaryDir": "${sourceDir}/out/build/${presetName}",
            "architecture": {
                "value": "x64",
                "strategy": "external"
            },
            "cacheVariables": {
                "CMAKE_BUILD_TYPE": "Debug",
                "CMAKE_INSTALL_PREFIX": "${sourceDir}/out/install/${presetName}",
                "BN_CORE_LIBRARY": "${sourceDir}",
                "BN_UI_LIBRARY": "${sourceDir}"
            },
            "vendor": {}
        }
    ]
}